vec2_math/__init__.py
vec2_math/py.typed
vec2_math-0.7.0.dist-info/WHEEL
vec2_math-0.7.0.dist-info/METADATA
vec2_math-0.7.0.dist-info/RECORD
