Metadata-Version: 2.4
Name: vec2-math
Version: 0.7.0
Summary: basic vector functions in 2D
Author: Shay Hill
Author-email: Shay Hill <shay_public@hotmail.com>
License-Expression: MIT
Requires-Python: >=3.10
